hangouts_helper/__init__.py
hangouts_helper/api.py
hangouts_helper/handler.py
hangouts_helper/message.py
hangouts_helper/version.py
hangouts_helper-19.12.0.dist-info/LICENSE
hangouts_helper-19.12.0.dist-info/METADATA
hangouts_helper-19.12.0.dist-info/WHEEL
hangouts_helper-19.12.0.dist-info/top_level.txt
hangouts_helper-19.12.0.dist-info/RECORD
