Metadata-Version: 2.1
Name: hangouts-helper
Version: 19.12.0
Summary: Helper Python classes for handling and responding to Hangouts Chat events
Home-page: http://github.com/christippett/hangouts-helper
Author: Chris Tippett
Author-email: c.tippett@gmail.com
License: MIT
Platform: UNKNOWN
Classifier: Environment :: Web Environment
Classifier: Framework :: Django
Classifier: Operating System :: OS Independent
Classifier: License :: OSI Approved :: MIT License
Classifier: Programming Language :: Python
Classifier: Programming Language :: Python :: 3.4
Classifier: Programming Language :: Python :: 3.5
Classifier: Programming Language :: Python :: 3.6
Classifier: Programming Language :: Python :: 3.7
Requires-Dist: google-api-python-client
Requires-Dist: google-auth-httplib2
Requires-Dist: setuptools
